glitter_events/__init__.py
glitter_events/admin.py
glitter_events/apps.py
glitter_events/mixins.py
glitter_events/models.py
glitter_events/search_indexes.py
glitter_events/urls.py
glitter_events/views.py
glitter_events/migrations/0001_initial.py
glitter_events/migrations/0002_slug_unique.py
glitter_events/migrations/0003_optional_end.py
glitter_events/migrations/0004_add_tags.py
glitter_events/migrations/0005_rename_location_to_address.py
glitter_events/migrations/0006_add_locations.py
glitter_events/migrations/__init__.py
glitter_events/templates/glitter/blocks/upcomingeventsblock.html
glitter_events/templates/search/indexes/glitter_events/event_text.txt
glitter_events/templatetags/__init__.py
glitter_events/templatetags/events_tags.py
django_glitter_events-0.1.8.dist-info/LICENSE
django_glitter_events-0.1.8.dist-info/METADATA
django_glitter_events-0.1.8.dist-info/WHEEL
django_glitter_events-0.1.8.dist-info/top_level.txt
django_glitter_events-0.1.8.dist-info/RECORD
