Metadata-Version: 2.1
Name: django-glitter-events
Version: 0.1.8
Summary: Glitter Events for Django
Home-page: https://github.com/developersociety/django-glitter-events
Maintainer: The Developer Society
Maintainer-email: studio@dev.ngo
License: BSD
Platform: any
Classifier: Environment :: Web Environment
Classifier: Framework :: Django
Classifier: License :: OSI Approved :: BSD License
Classifier: Operating System :: OS Independent
Classifier: Programming Language :: Python
Classifier: Programming Language :: Python :: 2
Classifier: Programming Language :: Python :: 2.7
Classifier: Programming Language :: Python :: 3
Classifier: Programming Language :: Python :: 3.3
Classifier: Programming Language :: Python :: 3.4
Classifier: Programming Language :: Python :: 3.5
Requires-Dist: django-glitter
Requires-Dist: django-taggit (>=0.21.3)
